{
  "summary": "The batch of synthetic samples demonstrates good coverage across all attributes, but there are some missing combinations and potential near-duplicates. The diversity of scenarios is generally well-represented, though some edge cases could be further explored.",
  "missing_modes": [],
  "overrepresented_modes": [
    "fragmented",
    "concise"
  ],
  "near_duplicate_rate": 0.15,
  "recommendations": [
    "Encourage the generation of more varied phrasing to reduce near-duplicates.",
    "Include more edge cases and rare scenarios to enhance diversity.",
    "Ensure a balanced representation of styles, particularly by introducing more verbose and emotional styles."
  ],
  "coverage": {
    "intent": 1.0,
    "difficulty": 1.0,
    "ambiguity": 1.0,
    "style": 1.0,
    "noise": 1.0,
    "scenario_type": 1.0
  }
}